pelican/themes/smallweb/__init__.py
pelican/themes/smallweb/static/css/codecolor/bleak.css
pelican/themes/smallweb/static/css/fonts.css
pelican/themes/smallweb/static/css/style.css
pelican/themes/smallweb/templates/archives.html
pelican/themes/smallweb/templates/article.html
pelican/themes/smallweb/templates/author.html
pelican/themes/smallweb/templates/base.html
pelican/themes/smallweb/templates/category.html
pelican/themes/smallweb/templates/index.html
pelican/themes/smallweb/templates/page.html
pelican/themes/smallweb/templates/partial/feedlinks.html
pelican/themes/smallweb/templates/partial/footer.html
pelican/themes/smallweb/templates/partial/loop.html
pelican/themes/smallweb/templates/partial/macros.j2
pelican/themes/smallweb/templates/partial/navigation.html
pelican/themes/smallweb/templates/partial/pagination.html
pelican/themes/smallweb/templates/tag.html
pelican/themes/smallweb/templates/tags.html
pelican_theme_smallweb-2022.6.28.dist-info/LICENSE
pelican_theme_smallweb-2022.6.28.dist-info/WHEEL
pelican_theme_smallweb-2022.6.28.dist-info/METADATA
pelican_theme_smallweb-2022.6.28.dist-info/RECORD
