Metadata-Version: 2.1
Name: pelican-theme-smallweb
Version: 2022.6.28
Summary: SmallWeb theme for Pelican static site generator
License: Apache-2.0
Keywords: blog,pelican,theme
Author: Vitaly Potyarkin
Author-email: sio.wtf@gmail.com
Classifier: Environment :: Console
Classifier: Intended Audience :: Developers
Classifier: License :: OSI Approved :: Apache Software License
Classifier: Programming Language :: Python :: 2
Classifier: Programming Language :: Python :: 2.7
Classifier: Programming Language :: Python :: 3
Classifier: Programming Language :: Python :: 3.10
Classifier: Programming Language :: Python :: 3.4
Classifier: Programming Language :: Python :: 3.5
Classifier: Programming Language :: Python :: 3.6
Classifier: Programming Language :: Python :: 3.7
Classifier: Programming Language :: Python :: 3.8
Classifier: Programming Language :: Python :: 3.9
Requires-Dist: pelican
Requires-Dist: setuptools
Project-URL: Issue Tracker, https://github.com/sio/pelican-smallweb
